thisismy/__init__.py
thisismy/testpackage/__init__.py
thisismy/testpackage/_version.py
thisismy/testpackage/client.py
thisismy.testpackage-0.0.7.dist-info/LICENSE
thisismy.testpackage-0.0.7.dist-info/METADATA
thisismy.testpackage-0.0.7.dist-info/WHEEL
thisismy.testpackage-0.0.7.dist-info/top_level.txt
thisismy.testpackage-0.0.7.dist-info/RECORD
