Metadata-Version: 2.1
Name: thisismy.testpackage
Version: 0.0.7
Summary: Just testing
Author-email: Patryk Orzechowski <patryk@upenn.edu>
Maintainer-email: Patryk Orzechowski <patryk@upenn.edu>
License: Apache License
Project-URL: homepage, http://pennsieve.io
Project-URL: documentation, http://pennsieve.io
Project-URL: repository, http://pennsieve.io
Project-URL: changelog, http://pennsieve.io
Keywords: data science,datasets
Classifier: Development Status :: 4 - Beta
Classifier: Intended Audience :: Developers
Classifier: Intended Audience :: Information Technology
Classifier: Intended Audience :: Science/Research
Classifier: License :: OSI Approved :: Apache Software License
Classifier: Programming Language :: Python :: 3.10
Classifier: Topic :: Scientific/Engineering
Classifier: Topic :: Scientific/Engineering :: Bio-Informatics
Classifier: Topic :: Scientific/Engineering :: Information Analysis
Classifier: Topic :: Software Development
Classifier: Topic :: Software Development :: Libraries
Classifier: Topic :: Software Development :: Libraries :: Python Modules
Requires-Python: >=3.10
License-File: LICENSE
Provides-Extra: test
Requires-Dist: pytest ~=7.2 ; extra == 'test'
Requires-Dist: pytest-cov ; extra == 'test'
Requires-Dist: pytest-mock ; extra == 'test'
Requires-Dist: flake8 ; extra == 'test'
Requires-Dist: black ; extra == 'test'
Requires-Dist: responses ; extra == 'test'
